{"nodes": [{"id": "agam_benchmarks_harness_agam_harness_py", "label": "agam_harness.py", "file_type": "code", "source_file": "agam\\benchmarks\\harness\\agam_harness.py", "source_location": "L1"}, {"id": "agam_harness_agamharness", "label": "AgamHarness", "file_type": "code", "source_file": "agam\\benchmarks\\harness\\agam_harness.py", "source_location": "L12"}, {"id": "baseharness", "label": "BaseHarness", "file_type": "code", "source_file": "", "source_location": ""}, {"id": "agam_harness_agamharness_prepare", "label": ".prepare()", "file_type": "code", "source_file": "agam\\benchmarks\\harness\\agam_harness.py", "source_location": "L16"}, {"id": "agam_harness_is_windows", "label": "_is_windows()", "file_type": "code", "source_file": "agam\\benchmarks\\harness\\agam_harness.py", "source_location": "L97"}], "edges": [{"source": "agam_benchmarks_harness_agam_harness_py", "target": "os", "relation": "imports", "confidence": "EXTRACTED", "source_file": "agam\\benchmarks\\harness\\agam_harness.py", "source_location": "L3", "weight": 1.0}, {"source": "agam_benchmarks_harness_agam_harness_py", "target": "pathlib", "relation": "imports_from", "confidence": "EXTRACTED", "source_file": "agam\\benchmarks\\harness\\agam_harness.py", "source_location": "L4", "weight": 1.0}, {"source": "agam_benchmarks_harness_agam_harness_py", "target": "shutil", "relation": "imports_from", "confidence": "EXTRACTED", "source_file": "agam\\benchmarks\\harness\\agam_harness.py", "source_location": "L5", "weight": 1.0}, {"source": "agam_benchmarks_harness_agam_harness_py", "target": "sys", "relation": "imports", "confidence": "EXTRACTED", "source_file": "agam\\benchmarks\\harness\\agam_harness.py", "source_location": "L6", "weight": 1.0}, {"source": "agam_benchmarks_harness_agam_harness_py", "target": "benchmarks_harness_base_harness", "relation": "imports_from", "confidence": "EXTRACTED", "source_file": "agam\\benchmarks\\harness\\agam_harness.py", "source_location": "L8", "weight": 1.0}, {"source": "agam_benchmarks_harness_agam_harness_py", "target": "benchmarks_infrastructure_utils", "relation": "imports_from", "confidence": "EXTRACTED", "source_file": "agam\\benchmarks\\harness\\agam_harness.py", "source_location": "L9", "weight": 1.0}, {"source": "agam_benchmarks_harness_agam_harness_py", "target": "agam_harness_agamharness", "relation": "contains", "confidence": "EXTRACTED", "source_file": "agam\\benchmarks\\harness\\agam_harness.py", "source_location": "L12", "weight": 1.0}, {"source": "agam_harness_agamharness", "target": "baseharness", "relation": "inherits", "confidence": "EXTRACTED", "source_file": "agam\\benchmarks\\harness\\agam_harness.py", "source_location": "L12", "weight": 1.0}, {"source": "agam_harness_agamharness", "target": "agam_harness_agamharness_prepare", "relation": "method", "confidence": "EXTRACTED", "source_file": "agam\\benchmarks\\harness\\agam_harness.py", "source_location": "L16", "weight": 1.0}, {"source": "agam_benchmarks_harness_agam_harness_py", "target": "agam_harness_is_windows", "relation": "contains", "confidence": "EXTRACTED", "source_file": "agam\\benchmarks\\harness\\agam_harness.py", "source_location": "L97", "weight": 1.0}, {"source": "agam_harness_agamharness_prepare", "target": "agam_harness_is_windows", "relation": "calls", "confidence": "EXTRACTED", "source_file": "agam\\benchmarks\\harness\\agam_harness.py", "source_location": "L28", "weight": 1.0}], "raw_calls": [{"caller_nid": "agam_harness_agamharness_prepare", "callee": "resolve_agam_driver_command", "source_file": "agam\\benchmarks\\harness\\agam_harness.py", "source_location": "L23"}, {"caller_nid": "agam_harness_agamharness_prepare", "callee": "str", "source_file": "agam\\benchmarks\\harness\\agam_harness.py", "source_location": "L24"}, {"caller_nid": "agam_harness_agamharness_prepare", "callee": "int", "source_file": "agam\\benchmarks\\harness\\agam_harness.py", "source_location": "L25"}, {"caller_nid": "agam_harness_agamharness_prepare", "callee": "get", "source_file": "agam\\benchmarks\\harness\\agam_harness.py", "source_location": "L25"}, {"caller_nid": "agam_harness_agamharness_prepare", "callee": "bool", "source_file": "agam\\benchmarks\\harness\\agam_harness.py", "source_location": "L26"}, {"caller_nid": "agam_harness_agamharness_prepare", "callee": "get", "source_file": "agam\\benchmarks\\harness\\agam_harness.py", "source_location": "L26"}, {"caller_nid": "agam_harness_agamharness_prepare", "callee": "bool", "source_file": "agam\\benchmarks\\harness\\agam_harness.py", "source_location": "L27"}, {"caller_nid": "agam_harness_agamharness_prepare", "callee": "get", "source_file": "agam\\benchmarks\\harness\\agam_harness.py", "source_location": "L27"}, {"caller_nid": "agam_harness_agamharness_prepare", "callee": "with_suffix", "source_file": "agam\\benchmarks\\harness\\agam_harness.py", "source_location": "L28"}, {"caller_nid": "agam_harness_agamharness_prepare", "callee": "str", "source_file": "agam\\benchmarks\\harness\\agam_harness.py", "source_location": "L41"}, {"caller_nid": "agam_harness_agamharness_prepare", "callee": "str", "source_file": "agam\\benchmarks\\harness\\agam_harness.py", "source_location": "L43"}, {"caller_nid": "agam_harness_agamharness_prepare", "callee": "str", "source_file": "agam\\benchmarks\\harness\\agam_harness.py", "source_location": "L45"}, {"caller_nid": "agam_harness_agamharness_prepare", "callee": "append", "source_file": "agam\\benchmarks\\harness\\agam_harness.py", "source_location": "L48"}, {"caller_nid": "agam_harness_agamharness_prepare", "callee": "str", "source_file": "agam\\benchmarks\\harness\\agam_harness.py", "source_location": "L53"}, {"caller_nid": "agam_harness_agamharness_prepare", "callee": "str", "source_file": "agam\\benchmarks\\harness\\agam_harness.py", "source_location": "L57"}, {"caller_nid": "agam_harness_agamharness_prepare", "callee": "str", "source_file": "agam\\benchmarks\\harness\\agam_harness.py", "source_location": "L59"}, {"caller_nid": "agam_harness_agamharness_prepare", "callee": "append", "source_file": "agam\\benchmarks\\harness\\agam_harness.py", "source_location": "L62"}, {"caller_nid": "agam_harness_agamharness_prepare", "callee": "str", "source_file": "agam\\benchmarks\\harness\\agam_harness.py", "source_location": "L63"}, {"caller_nid": "agam_harness_agamharness_prepare", "callee": "str", "source_file": "agam\\benchmarks\\harness\\agam_harness.py", "source_location": "L71"}, {"caller_nid": "agam_harness_agamharness_prepare", "callee": "str", "source_file": "agam\\benchmarks\\harness\\agam_harness.py", "source_location": "L75"}, {"caller_nid": "agam_harness_agamharness_prepare", "callee": "append", "source_file": "agam\\benchmarks\\harness\\agam_harness.py", "source_location": "L78"}, {"caller_nid": "agam_harness_agamharness_prepare", "callee": "Path", "source_file": "agam\\benchmarks\\harness\\agam_harness.py", "source_location": "L80"}, {"caller_nid": "agam_harness_agamharness_prepare", "callee": "which", "source_file": "agam\\benchmarks\\harness\\agam_harness.py", "source_location": "L80"}, {"caller_nid": "agam_harness_agamharness_prepare", "callee": "str", "source_file": "agam\\benchmarks\\harness\\agam_harness.py", "source_location": "L80"}, {"caller_nid": "agam_harness_agamharness_prepare", "callee": "which", "source_file": "agam\\benchmarks\\harness\\agam_harness.py", "source_location": "L80"}, {"caller_nid": "agam_harness_agamharness_prepare", "callee": "str", "source_file": "agam\\benchmarks\\harness\\agam_harness.py", "source_location": "L80"}, {"caller_nid": "agam_harness_agamharness_prepare", "callee": "PreparedBenchmark", "source_file": "agam\\benchmarks\\harness\\agam_harness.py", "source_location": "L82"}, {"caller_nid": "agam_harness_agamharness_prepare", "callee": "str", "source_file": "agam\\benchmarks\\harness\\agam_harness.py", "source_location": "L84"}, {"caller_nid": "agam_harness_agamharness_prepare", "callee": "get", "source_file": "agam\\benchmarks\\harness\\agam_harness.py", "source_location": "L84"}, {"caller_nid": "agam_harness_agamharness_prepare", "callee": "str", "source_file": "agam\\benchmarks\\harness\\agam_harness.py", "source_location": "L87"}, {"caller_nid": "agam_harness_agamharness_prepare", "callee": "get", "source_file": "agam\\benchmarks\\harness\\agam_harness.py", "source_location": "L87"}]}