{"nodes": [{"id": "agam_benchmarks_infrastructure_init_py", "label": "__init__.py", "file_type": "code", "source_file": "agam\\benchmarks\\infrastructure\\__init__.py", "source_location": "L1"}, {"id": "init_rationale_1", "label": "Benchmark infrastructure for the Agam benchmark workspace.", "file_type": "rationale", "source_file": "agam\\benchmarks\\infrastructure\\__init__.py", "source_location": "L1"}], "edges": [{"source": "init_rationale_1", "target": "agam_benchmarks_infrastructure_init_py", "relation": "rationale_for", "confidence": "EXTRACTED", "source_file": "agam\\benchmarks\\infrastructure\\__init__.py", "source_location": "L1", "weight": 1.0}], "raw_calls": []}